openlsa/__init__.py
openlsa/openlsa.py
openlsa/phase.py
openlsa/utils.py
openlsa-0.9.88.dist-info/LICENSE
openlsa-0.9.88.dist-info/METADATA
openlsa-0.9.88.dist-info/WHEEL
openlsa-0.9.88.dist-info/RECORD
