Metadata-Version: 2.1
Name: openlsa
Version: 0.9.88
Summary: A LSA tool to compute full-field displacement from an image series of periodic patterns
License: GPL-2.0-only
Author: IP's Experimental Mechanics team Blaysat
Author-email: expmech.ip@gmail.fr
Requires-Python: >=3.9,<3.13
Classifier: License :: OSI Approved :: GNU General Public License v2 (GPLv2)
Classifier: Programming Language :: Python :: 3
Classifier: Programming Language :: Python :: 3.9
Classifier: Programming Language :: Python :: 3.10
Classifier: Programming Language :: Python :: 3.11
Classifier: Programming Language :: Python :: 3.12
Requires-Dist: boto3 (>=1.34.39,<2.0.0)
Requires-Dist: matplotlib (>=3.8.1,<4.0.0)
Requires-Dist: numpy (>=1.26.2,<2.0.0)
Requires-Dist: opencv-python (>=4.8.1.78,<5.0.0.0)
Requires-Dist: pillow (>=10.1.0,<11.0.0)
Requires-Dist: scikit-image (>=0.22.0,<0.23.0)
Requires-Dist: scipy (>=1.11.3,<2.0.0)
